randomak/__init__.py
randomak/randomak.py
randomak-0.1.0.dist-info/licenses/LICENSE
randomak-0.1.0.dist-info/METADATA
randomak-0.1.0.dist-info/WHEEL
randomak-0.1.0.dist-info/top_level.txt
randomak-0.1.0.dist-info/RECORD
