Metadata-Version: 2.4
Name: RandomAK
Version: 0.1.0
Summary: A Python package for enhanced randomization functions
Home-page: https://github.com/anbukumaran1/RandomAK
Author: AnbuKumaran Arangaperumal
Author-email: anbuku12345@gmail.com
License: MIT
Classifier: Programming Language :: Python :: 3
Classifier: Operating System :: OS Independent
Requires-Python: >=3.6
License-File: LICENSE
Dynamic: author
Dynamic: author-email
Dynamic: classifier
Dynamic: description
Dynamic: description-content-type
Dynamic: home-page
Dynamic: license
Dynamic: license-file
Dynamic: requires-python
Dynamic: summary
